{
  "automoveis": [
    {
      "id": 1,
      "nome": "jETOUR",
      "modelo": "X90 plus",
      "nome_catalogo": "X90_Plus_Impressão_A4_Papel_Couchê.pdf",
      "link_catalogo": "http://teste1.bcc.ao/gets/catalogos/X90_Plus_Impressão_A4_Papel_Couchê.pdf",
      "cor": "preta",
      "slogan": "aproveite a vida e sua viagem",
      "capa": "http://teste1.bcc.ao/gets/images/jetur/pagina_inicial/X90/capa.png",
      "capa_2": "http://teste1.bcc.ao/gets/images/jetur/X90Plus/KV.png",
      "description": "ULTRA ESPAÇOSO, MOSTRANDO EXTREMO LUXO",
      "visao_geral": [
        {
          "foto_info": "http://teste1.bcc.ao/gets/images/jetur/X90Plus/Interior/electronic-gear-shifter.png",
          "capa": "http://teste1.bcc.ao/gets/images/jetur/X90Plus/Color/JETOUR_X90_zilong_white_013.png"
        }
      ],
      "cores": [
        {
          "nome": "preto",
          "fundo": "bg-black",
          "link": "http://teste1.bcc.ao/gets/images/jetur/X90Plus/Color/JETOUR_X90_zilong_black_013.png"
        },
        {
          "nome": "cinzento",
          "fundo": "bg-grey-lighten-2",
          "link": "http://teste1.bcc.ao/gets/images/jetur/X90Plus/Color/JETOUR_X90_zilong_grey_013.png"
        },
        {
          "nome": "violeta",
          "fundo": "bg-pink-darken-4",
          "link": "http://teste1.bcc.ao/gets/images/jetur/X90Plus/Color/JETOUR_X90_zilong_violet_013.png"
        },
        {
          "nome": "braco",
          "fundo": "bg-white",
          "link": "http://teste1.bcc.ao/gets/images/jetur/X90Plus/Color/JETOUR_X90_zilong_white_013.png"
        },
        {
          "nome": "azul",
          "fundo": "bg-light-blue-darken-4",
          "link": "http://teste1.bcc.ao/gets/images/jetur/X90Plus/Color/JETOUR_X90PLUS_008-PNG.png"
        }
      ],
      "desepenho": [
        {
          "titulo": "Motor 2.0 T+7DCT",
          "foto_depenho": "http://teste1.bcc.ao/gets/images/jetur/X90Plus/desepenho/1.jpg",
          "descricao": "O X90 PLUS está equipado com um motor potente de 2.0T, combinado com uma transmissão de 7 dupla embreagem molhada, que pode produzir 254HP, a aceleração de 100 km é inferior a 8 segundos. Pode lidar com várias condições de estrada e trazer-lhe o máximo prazer de condução e experiência."
        }
      ],
      "exterior": [
        {
          "titulo": "Excelente imagem",
          "conteudo": "Excelente formato hexagonal de ar prestígio, grade cromada quadrada calma e equipada com um conjunto de faróis de LED Matrix, o design geral é moderno e elegante.",
          "foto": "http://teste1.bcc.ao/gets/images/jetur/X90Plus/Exterior/2.png"
        }
      ],
      "interior": [
        {
          "titulo": "Interior de luxo, cabine tranquila",
          "conteudo": "O layout geral é simples e elegante, com espaço para modelos MPV. Configuração luxuosa e adoção de tecnologias de pacote acústico silencioso NVH 24, desfrute de um cockpit silencioso de 36db",
          "foto": "http://teste1.bcc.ao/gets/images/jetur/X90Plus/Interior/electronic-gear-shifter.png"
        }
      ],
      "tecnologia": [
        {
          "titulo": "Estacionamento Panorâmico 360°",
          "conteudo": "A câmera panorâmica 360° auxilia o motorista com uma visão panorâmica e o Parking Assist, bem como ao estacionar e manobrar. A câmera torna visível a área imediatamente ao redor do veículo, tanto do ponto de vista aéreo quanto abaixo da linha da janela.",
          "foto": "http://teste1.bcc.ao/gets/images/jetur/X90Plus/Technology/360 degree panoramic parking.png"
        }
      ],
      "info": [
        {
          "t1": " 2850 milímeros",
          "t2": "254HP",
          "t3": "2.0T+7DCT",
          "desc1": "Distância entre os eixos",
          "desc2": "Potência máxima",
          "desc3": "Motor"
        }
      ]
    },
    {
      "id": 2,
      "nome": "JETOUR",
      "modelo": "X70 plus",
      "nome_catalogo": "X70_Plus_Impressão_A4_Papel_Couchê.pdf",
      "link_catalogo": "http://teste1.bcc.ao/gets/catalogos/X70_Plus_Impressão_A4_Papel_Couchê.pdf",
      "cor": "azul",
      "slogan": "aproveite a vida e sua viagem",
      "capa": "http://teste1.bcc.ao/gets/images/jetur/pagina_inicial/X70Plus/PNG-2.png",
      "capa_2": "http://teste1.bcc.ao/gets/images/jetur/X70Plus/KV.png",
      "description": "UMA EXPRESSÃO DE ELEGÂNCIA",
      "visao_geral": [
        {
          "foto_info": "http://teste1.bcc.ao/gets/images/jetur/X70Plus/Interior/1.jpg",
          "capa": "http://teste1.bcc.ao/gets/images/jetur/X70Plus/Color/white.png"
        }
      ],
      "cores": [
        {
          "nome": "preto",
          "fundo": "bg-black",
          "link": "http://teste1.bcc.ao/gets/images/jetur/X70Plus/Color/black.png"
        },
        {
          "nome": "vermelho",
          "fundo": "bg-red-darken-4",
          "link": "http://teste1.bcc.ao/gets/images/jetur/X70Plus/Color/red.png"
        },

        {
          "nome": "roxo",
          "fundo": "bg-pink-darken-2",
          "link": "http://teste1.bcc.ao/gets/images/jetur/X70Plus/Color/roxo.png"
        },
        {
          "nome": "braco",
          "fundo": "bg-white",
          "link": "http://teste1.bcc.ao/gets/images/jetur/X70Plus/Color/white.png"
        },
        {
          "nome": "azul escuro",
          "fundo": "bg-light-blue-darken-4",
          "link": "http://teste1.bcc.ao/gets/images/jetur/X70Plus/Color/azul-escuro.png"
        }
      ],
      "desepenho": [
        {
          "titulo": "Motor Potente",
          "descricao": "Um motor 1.6L turboalimentado, com 197 cavalos acoplado a uma transmissão de dupla embreagem de 7 velocidades, resultando em uma experiência de direção suave e eficiente.",
          "foto_depenho": "http://teste1.bcc.ao/gets/images/jetur/X70Plus/Performance/1.jpg"
        }
      ],
      "exterior": [
        {
          "titulo": "Exterior Elegante",
          "conteudo": "Lorem impsum dolor sit amet Lorem impsum dolor sit amet Lorem impsum dolor sit amet",
          "foto": "http://teste1.bcc.ao/gets/images/jetur/X70Plus/Exterior/3.png"
        }
      ],
      "interior": [
        {
          "titulo": "Tecnologia Avançada",
          "conteudo": "O Jetour X70 Plus Top está equipado com um avançado sistema de entretenimento compatível com smartphones de última geração. Um painel touchscreen que controla o sistema de ar condicionado. Um cockpit digital que oferece sistemas inteligentes para uma experiência de condução mais segura, inteligente e rica.",
          "foto": "http:/este1.bcc.ao/gets/images/jetur/X70Plus/Interior/4.jpg"
        }
      ],
      "tecnologia": [
        {
          "titulo": "Tech Tech",
          "conteudo": "Lorem impsum dolor sit amet Lorem impsum dolor sit amet Lorem impsum dolor sit amet Lorem impsum dolor sit amet",
          "foto": "http://teste1.bcc.ao/gets/images/jetur/X70Plus/Tech/LDWS.png"
        }
      ],
      "info": [
        {
          "t1": " 2745 milímeros",
          "t2": "290HP",
          "t3": "2.6T+7DCT",
          "desc1": "Distância entre os eixos",
          "desc2": "Potência máxima",
          "desc3": "Motor"
        }
      ]
    },
    {
      "id": 3,
      "nome": "JETOUR",
      "modelo": "X70",
      "nome_catalogo": "X70_Impressão_A4_Papel_Couchê.pdf",
      "link_catalogo": "http://teste1.bcc.ao/gets/catalogos/X70_Impressão_A4_Papel_Couchê.pdf",
      "cor": "azul",
      "slogan": "aproveite a vida e sua viagem",
      "capa": "http://teste1.bcc.ao/gets/images/jetur/pagina_inicial/X70/X70-2.png",
      "capa_2": "http://teste1.bcc.ao/gets/images/jetur/pagina_inicial/X70/X70-2.png",
      "description": "O Melhor e Prático carro para família angola",
      "visao_geral": [
        {
          "foto_info": "http://teste1.bcc.ao/gets/images/jetur/X70/Interior/Cockpit Inteligente.jpg",
          "capa": "http://teste1.bcc.ao/gets/images/jetur/X90Plus/Color/JETOUR_X90_zilong_white_013.png"
        }
      ],
      "cores": [
        {
          "nome": "preto",
          "fundo": "bg-black",
          "link": "http://teste1.bcc.ao/gets/images/jetur/X70/Color/X70_240T_Black_Side-PNG.png"
        },
        {
          "nome": "braco",
          "fundo": "bg-white",
          "link": "http://teste1.bcc.ao/gets/images/jetur/X70/Color/X70_240T_White_Side-PNG.png"
        },
        {
          "nome": "azul",
          "fundo": "bg-light-blue-darken-4",
          "link": "http://teste1.bcc.ao/gets/images/jetur/X70/Color/X70_240T_Blue_Side-PNG.png"
        }
      ],
      "desepenho": [
        {
          "titulo": "Motor Turboalimentado",
          "descricao": "O Jetour X70 Intermedio vem com um motor turbo 1.5T emparelhado com uma transmissão automática de 8 velocidades que gera 156 HP e se destaca no consumo reduzido de combustível, suficiente para uma ultrapassagem rápida.",
          "foto_depenho": "http://teste1.bcc.ao/gets/images/jetur/X70/Performance/TJX70J-(40).png"
        }
      ],
      "exterior": [
        {
          "titulo": "Modelagem esportiva altamente reconhecível",
          "conteudo": "X70 intermedio possui maior espaçamento de grade para que sua identificação seja alta e represente uma classe alta. A lâmpada de guia de luz de alta luminância em comparação com a lâmpada halógena tradicional, tem as vantagens de longa vida útil e mais ecologicamente correta.",
          "foto": "http://teste1.bcc.ao/gets/images/jetur/X70/Exterior/1.jpg"
        }
      ],
      "interior": [
        {
          "titulo": "Interiores com estilo esportivo",
          "conteudo": "Desde o impressionante volante tipo D e pedais de metal polido até o botão para multimídia, o Jetour X70 intermedia tem um design interior esportivo que o envolve em um ambiente tecnológico apoiado por qualidade de classe mundial.",
          "foto": "http://teste1.bcc.ao/gets/images/jetur/X70/Interior/Interiores-desportivos-e-elegantes.jpg"
        }
      ],
      "tecnologia": [
        {
          "titulo": "Alto fator de segurança EPB+AUTOHOLD",
          "conteudo": "função AUTOHOLD inteligente permite que a roda traseira seja freada automaticamente quando o veículo está parado em um sinal vermelho ou estacionado em uma subida ou descida. O motorista não terá que pisar no freio o tempo todo para manter o carro parado, mesmo que a transmissão automática esteja no modo D. A função Auto Hold será ativada assim que o botão “AUTHOLD” for pressionado, e uma pisada suave no acelerador liberará o freio. Este recurso inteligente dissipa completamente a preocupação de escorregar no início da subida",
          "foto": "http://teste1.bcc.ao/gets/images/jetur/X70/Tech/1jpg"
        }
      ],
      "info": [
        {
          "t1": "2745 milímeros",
          "t2": "156HP",
          "t3": "1.5T + BAT",
          "desc1": "Distância entre os eixos",
          "desc2": "Potência máxima",
          "desc3": "Motor"
        }
      ]
    }
  ]
}
